decoupled/__init__.py
decoupled/decoupled.py
decoupled-0.0.7.dist-info/DESCRIPTION.rst
decoupled-0.0.7.dist-info/METADATA
decoupled-0.0.7.dist-info/RECORD
decoupled-0.0.7.dist-info/WHEEL
decoupled-0.0.7.dist-info/metadata.json
decoupled-0.0.7.dist-info/top_level.txt
tests/__init__.py
tests/test_decoupled.py
