Metadata-Version: 2.1
Name: decoupled
Version: 0.0.7
Summary: Run a python function (e.g., a test) in it's own process
Home-page: https://gitlab.com/UncleOwen/decoupled
Author: Sören Glimm
Author-email: git@uncleowen.de
License: UNKNOWN
Platform: UNKNOWN
Classifier: Programming Language :: Python :: 3
Classifier: License :: OSI Approved :: Apache Software License
Classifier: Operating System :: OS Independent
Classifier: Development Status :: 3 - Alpha
